gssetting/__init__.py
gssetting/google_spreadsheet.py
gssetting/gssetting.py
gssetting/inheritance.py
gssetting/model/__init__.py
gssetting/model/gssetting.py
gssetting/model/value_render_option.py
gssetting-0.0.1.dist-info/LICENSE
gssetting-0.0.1.dist-info/METADATA
gssetting-0.0.1.dist-info/WHEEL
gssetting-0.0.1.dist-info/top_level.txt
gssetting-0.0.1.dist-info/RECORD
