Metadata-Version: 2.1
Name: gssetting
Version: 0.0.1
Summary: Load setting value from Google Sheets
Home-page: https://github.com/deresmos/gssetting
Author: deresmos
Author-email: deresmos@google.com
License: MIT License
Keywords: tools
Platform: UNKNOWN
Requires-Python: >=3.7
Requires-Dist: google-auth
Requires-Dist: gspread
Requires-Dist: requests
